py_rouge-1.1.dist-info/METADATA
py_rouge-1.1.dist-info/RECORD
py_rouge-1.1.dist-info/WHEEL
py_rouge-1.1.dist-info/top_level.txt
rouge/__init__.py
rouge/example.py
rouge/rouge.py
rouge/rouge_augmented.py
rouge/synonyms.py
rouge/wordnet_key_value.txt
rouge/wordnet_key_value_special_cases.txt
