Metadata-Version: 2.1
Name: py-rouge
Version: 1.1
Summary: Full Python implementation of the ROUGE metric, producing same results as in the official perl implementation.
Home-page: https://github.com/Diego999/py-rouge
Author: Diego Antognini
Author-email: diegoantognini@gmail.com
License: Apache License 2.0
Platform: UNKNOWN
